Metadata-Version: 2.1
Name: pdfcollate
Version: 0.1.3
Summary: UNKNOWN
Home-page: https://github.com/RomainGehrig/PDFCollate
Author: Romain Gehrig
Author-email: romain.gehrig@gmail.com
License: MIT
Platform: UNKNOWN
Classifier: License :: OSI Approved :: MIT License
Classifier: Topic :: Printing
Classifier: Topic :: Office/Business
Classifier: Topic :: Multimedia :: Graphics :: Capture :: Scanners
Classifier: Operating System :: POSIX :: Linux
Classifier: Programming Language :: Python
Classifier: Programming Language :: Python :: 3 :: Only
Classifier: Programming Language :: Python :: 3
Requires-Python: >=3.6.0
License-File: LICENSE
